---
title: 匿名内部类反编译分析
category: Java SE
tag: 
 - 匿名内部类
 - 字节码
---



## 代码

```java
package cyclereference;
	
public class OuterClass {
	private String username="231";

	public void someMethod() {
		Runnable runnable = new Runnable() {
			@Override
			public void run() {
				System.out.println(username);
			}
		};

		runnable.run();
	}

	public static void main(String[] args) {
		OuterClass outerClass = new OuterClass();
		outerClass.someMethod();
	}
}

```

## 编译文件后

- OuterClass.class
- OuterClass$1.class

使用idea打开`OuterClass$1.class`

```java
//
// Source code recreated from a .class file by IntelliJ IDEA
// (powered by FernFlower decompiler)
//

package cyclereference;

class OuterClass$1 implements Runnable {
    OuterClass$1(OuterClass this$0) {
        this.this$0 = this$0;
    }

    public void run() {
        System.out.println(this.this$0.username);
    }
}

```

可以看到匿名内部类在编译之后，编译器会自动生成构造方法，并且把隐式参数this$0给当前的示例变量，也就是说`OuterClass$1`类中有一个`  final cyclereference.OuterClass this$0;`的成员变量。



## 生成的字节码

用`javap -c OuterClass$1.class`命令查看生成的字节码如下

```j
Compiled from "OuterClass.java"
class cyclereference.OuterClass$1 implements java.lang.Runnable {
  final cyclereference.OuterClass this$0;

  cyclereference.OuterClass$1(cyclereference.OuterClass);
    Code:
       0: aload_0
       1: aload_1
       2: putfield      #1                  // Field this$0:Lcyclereference/OuterClass;
       5: aload_0
       6: invokespecial #2                  // Method java/lang/Object."<init>":()V
       9: return

  public void run();
    Code:
       0: getstatic     #3                  // Field java/lang/System.out:Ljava/io/PrintStream;
       3: aload_0
       4: getfield      #1                  // Field this$0:Lcyclereference/OuterClass;
       7: getfield      #4                  // Field cyclereference/OuterClass.username:Ljava/lang/String;
      10: invokevirtual #5                  // Method java/io/PrintStream.println:(Ljava/lang/String;)V
      13: return
}
```

让我们通过使用 `javap -c OuterClass$1` 命令来解读匿名内部类 `OuterClass$1` 的字节码。

假设你在命令行中运行了以下命令：

```bash
javap -c cyclereference.OuterClass$1
```

你可能会看到类似以下的输出：

```text
Compiled from "OuterClass.java"
class cyclereference.OuterClass$1 implements java.lang.Runnable {
  final cyclereference.OuterClass this$0;

  cyclereference.OuterClass$1(cyclereference.OuterClass);
    Code:
       0: aload_0
       1: aload_1
       2: putfield      #1                  // Field this$0:Lcyclereference/OuterClass;
       5: aload_0
       6: invokespecial #2                  // Method java/lang/Object."<init>":()V
       9: return

  public void run();
    Code:
       0: getstatic     #3                  // Field java/lang/System.out:Ljava/io/PrintStream;
       3: aload_0
       4: getfield      #1                  // Field this$0:Lcyclereference/OuterClass;
       7: getfield      #4                  // Field cyclereference/OuterClass.username:Ljava/lang/String;
      10: invokevirtual #5                  // Method java/io/PrintStream.println:(Ljava/lang/String;)V
      13: return
}
```

### 解释字节码输出

#### 1. `this$0` 字段

```text
final cyclereference.OuterClass this$0;
```

- `this$0` 是一个 `final` 字段，用于保存对外部类 `OuterClass` 实例的引用。
- 这个字段允许匿名内部类 `OuterClass$1` 访问外部类的实例成员（变量和方法）。

#### 2. 构造方法

```text
cyclereference.OuterClass$1(cyclereference.OuterClass);
  Code:
     0: aload_0
     1: aload_1
     2: putfield      #1                  // Field this$0:Lcyclereference/OuterClass;
     5: aload_0
     6: invokespecial #2                  // Method java/lang/Object."<init>":()V
     9: return
```

- **`aload_0`**：将匿名内部类的当前实例 (`this`) 加载到操作数栈上。
- **`aload_1`**：将外部类 `OuterClass` 的实例（传递给构造方法的参数）加载到栈上。
- **`putfield #1`**：将栈顶的外部类实例赋值给 `this$0` 字段。`#1` 是常量池中表示 `this$0` 字段的引用，`Lcyclereference/OuterClass;` 表示这个字段的类型。
- **`aload_0`**：再次将匿名内部类的当前实例加载到栈上。
- **`invokespecial #2`**：调用父类（`Object`）的构造方法来初始化匿名内部类。
- **`return`**：返回，完成构造方法的执行。

#### 3. `run()` 方法

```text
public void run();
  Code:
     0: getstatic     #3                  // Field java/lang/System.out:Ljava/io/PrintStream;
     3: aload_0
     4: getfield      #1                  // Field this$0:Lcyclereference/OuterClass;
     7: getfield      #4                  // Field cyclereference/OuterClass.username:Ljava/lang/String;
    10: invokevirtual #5                  // Method java/io/PrintStream.println:(Ljava/lang/String;)V
    13: return
```

- **`getstatic #3`**：获取 `System.out` 的静态字段引用（类型为 `PrintStream`），并将其加载到栈上。`#3` 是常量池中 `System.out` 字段的引用。
- **`aload_0`**：将当前匿名内部类的实例 (`this`) 加载到栈上。
- **`getfield #1`**：通过 `this$0` 字段访问外部类 `OuterClass` 的实例。`#1` 是常量池中表示 `this$0` 字段的引用。
- **`getfield #4`**：从外部类实例中获取 `username` 字段的值。`#4` 是常量池中表示 `username` 字段的引用。
- **`invokevirtual #5`**：调用 `PrintStream.println(String)` 方法，将 `username` 的值打印到控制台。`#5` 是常量池中表示 `println` 方法的引用。
- **`return`**：返回，结束 `run()` 方法的执行。

### 关键点总结

- **`this$0` 字段**：匿名内部类持有外部类实例的引用，这是通过 `this$0` 字段实现的。这个引用使得匿名内部类可以访问外部类的成员（如 `username`）。
- **构造方法**：在匿名内部类的构造方法中，外部类的实例通过参数传递给匿名内部类，并赋值给 `this$0` 字段，从而建立两者之间的联系。
- **成员访问**：`run()` 方法中的 `this$0` 字段允许匿名内部类访问外部类的 `username` 字段，并通过 `System.out.println` 打印出来。

通过以上分析，`this$0` 字段的工作机制和作用得到了清晰的展现，它在字节码层面实现了匿名内部类对外部类的成员访问。





### 使用语法糖

```java
OuterClass.this.username
```

使用外部类.this来显示的表示外部类